{
  "Design Psychrometrics": "Design Psychrometrics",
  "Zone": "Зона",
  "Return Air": "Рециркулирующий воздух",
  "Outdoor Air": "Наружный воздух",
  "Entering Coil": "Entering Coil",
  "Leaving Coil": "Leaving Coil",
  "Supply Fan": "Приточный вентилятор",
  "Dry Bulb Temperature": "Температура по сухому термометру",
  "Humidity Ratio": "Humidity Ratio",
  "Temperature Difference": "Перепад температур",
  "System Name": "Имя системы",
  "Time of Peak": "Time of Peak",
  "Coil Air Flow Rate": "Coil Air Flow Rate",
  "Zone Space Sensible Load": "Zone Space Sensible Load",
  "Outdoor Air Flow Rate": "Расход наружного воздуха",
  "Percent Outdoor Air": "Percent Outdoor Air",
  "Air Specific Heat": "Air Specific Heat",
  "Air Density": "Плотность воздушной среды"
}